aws_polly-0.1.dist-info/DESCRIPTION.rst
aws_polly-0.1.dist-info/METADATA
aws_polly-0.1.dist-info/RECORD
aws_polly-0.1.dist-info/WHEEL
aws_polly-0.1.dist-info/entry_points.txt
aws_polly-0.1.dist-info/metadata.json
aws_polly-0.1.dist-info/top_level.txt
awspolly/__init__.py
