Metadata-Version: 2.0
Name: aws-polly
Version: 0.1
Summary: A better Speech Synthesis algorithm for AWS Polly
Home-page: UNKNOWN
Author: Terrillo Walls
Author-email: terrillo@terrillo.me
License: MIT
Keywords: aws,polly,speech synthesis
Platform: UNKNOWN
Classifier: Development Status :: 1 - Planning
Classifier: Programming Language :: Python
Requires-Dist: boto3
